{
  "kind": "collectionType",
  "collectionName": "eventos",
  "info": {
    "name": "Eventos",
    "description": ""
  },
  "options": {
    "increments": true,
    "timestamps": true,
    "draftAndPublish": true
  },
  "pluginOptions": {},
  "attributes": {
    "text": {
      "type": "string",
      "unique": false
    },
    "start": {
      "type": "string"
    },
    "end": {
      "type": "string"
    },
    "resource": {
      "type": "string"
    },
    "nombre": {
      "type": "string",
      "unique": true
    },
    "grupo": {
      "model": "grupo"
    }
  }
}
